{"height":23,"infinite":false,"layers":[{"data":[1,1,1,1,1,1,1,1,1,1,1,1,1,1,1,1,1,1,1,1,1,1,1,1,1,1,1,1,1,1,1,1,1,1,1,1,1,1,1,1,1,1,5,0,0,0,0,0,0,0,0,0,0,0,4,1,5,0,0,0,0,0,0,0,0,0,0,0,0,0,0,0,0,0,0,0,0,0,0,0,4,1,1,0,0,0,0,0,0,0,0,0,0,0,0,0,1,0,0,0,0,0,0,0,0,0,0,0,0,0,0,0,0,0,0,0,0,0,0,0,0,0,1,1,0,0,0,0,0,0,0,0,0,0,0,0,0,1,0,0,0,0,0,0,0,0,0,0,0,0,0,0,0,0,0,0,0,0,0,0,0,0,0,1,1,0,0,0,0,0,0,0,0,0,0,0,0,0,1,0,0,0,0,0,0,0,0,0,0,0,0,0,0,0,0,0,0,0,0,0,0,0,0,2,1,1,0,0,0,2,1,1,1,1,1,1,1,1,1,1,1,1,1,1,1,1,1,1,1,1,1,1,1,1,1,0,0,0,1,1,1,1,1,1,1,1,1,0,0,0,0,0,0,0,1,0,0,0,0,0,0,0,0,0,0,0,0,0,0,0,0,0,0,0,0,4,3,0,0,0,0,0,0,0,0,4,1,1,0,0,0,0,0,0,0,1,0,0,0,0,0,0,0,0,0,0,0,0,0,0,0,0,0,0,0,0,0,4,3,0,0,0,0,0,0,0,0,1,1,3,0,0,0,0,0,0,1,0,0,0,0,0,0,0,0,0,0,0,0,0,0,0,0,0,0,0,0,0,0,4,3,0,0,0,0,0,0,0,1,1,1,1,1,1,0,0,0,1,1,1,1,1,7,7,7,7,7,7,1,1,1,3,0,0,0,0,0,0,0,0,0,4,3,0,0,0,0,0,0,1,1,5,0,0,0,0,0,0,1,0,0,0,0,0,0,0,0,0,0,0,0,0,4,1,3,0,0,0,2,1,1,1,1,5,0,0,0,0,0,0,1,1,0,0,0,0,0,0,0,1,0,0,0,0,0,0,0,0,0,0,0,0,0,0,0,0,0,0,0,0,0,0,2,5,0,0,0,12,1,1,1,1,1,0,0,0,2,0,0,0,1,0,0,0,0,0,0,0,0,0,0,0,0,0,0,0,0,0,0,0,0,0,2,5,0,0,0,12,1,1,1,1,1,1,0,0,0,1,1,1,1,5,0,0,0,0,2,6,6,6,6,6,6,3,0,0,0,0,0,0,0,0,2,5,0,0,0,12,1,1,1,1,1,1,1,0,0,0,1,0,0,0,0,0,0,0,0,0,0,0,0,0,0,0,4,1,1,1,1,0,0,0,1,5,0,0,0,12,1,1,1,1,1,1,1,1,0,0,0,1,0,0,0,0,0,0,0,0,0,0,0,0,0,0,0,0,0,0,0,0,0,0,0,0,0,0,0,0,0,0,0,0,0,0,4,1,1,0,0,0,1,0,0,0,0,0,0,0,0,0,0,0,0,0,0,0,0,0,0,0,0,0,0,0,0,0,0,0,0,0,0,0,0,0,0,0,1,1,0,0,0,1,0,0,0,0,0,2,1,1,0,0,0,1,1,3,0,0,0,0,0,0,0,0,0,0,0,0,2,1,1,1,1,1,0,0,0,1,1,0,0,0,1,1,1,1,1,1,5,0,0,0,0,0,0,0,4,7,7,7,7,7,7,5,0,0,0,0,2,1,1,1,1,1,1,0,0,0,1,1,0,0,0,0,0,0,0,0,0,0,0,0,0,0,0,0,0,0,0,0,0,0,0,0,0,0,0,0,2,1,1,1,1,1,1,1,0,0,0,1,1,0,0,0,0,0,0,0,0,0,0,0,0,0,0,0,0,0,0,0,0,0,0,0,0,0,0,0,0,0,0,0,0,0,0,0,0,0,0,0,1,1,0,0,0,0,0,0,0,0,0,0,0,2,0,0,0,0,0,0,0,0,0,0,0,0,0,0,0,0,0,0,0,0,0,0,0,0,0,0,2,1,1,1,1,1,1,1,1,1,1,1,1,1,1,1,1,1,1,1,1,1,1,1,1,1,1,1,1,1,1,1,1,1,1,1,1,1,1,1,1,1,1],"height":23,"name":"Ground","opacity":1,"type":"tilelayer","visible":true,"width":41,"x":0,"y":0},{"draworder":"topdown","name":"Objects","objects":[{"gid":16,"height":64,"id":1,"name":"","properties":{"group":3},"propertytypes":{"group":"int"},"rotation":0,"type":"","visible":true,"width":64,"x":1200,"y":384},{"gid":16,"height":64,"id":2,"name":"","properties":{"group":1},"propertytypes":{"group":"int"},"rotation":0,"type":"","visible":true,"width":64,"x":944,"y":736},{"height":64,"id":3,"name":"","properties":{"dx":0,"dy":-2,"group":3},"propertytypes":{"dx":"float","dy":"float","group":"int"},"rotation":0,"type":"platform","visible":true,"width":32,"x":1120,"y":480},{"height":64,"id":5,"name":"","properties":{"dx":0,"dy":2,"group":1},"propertytypes":{"dx":"float","dy":"float","group":"int"},"rotation":0,"type":"platform","visible":true,"width":32,"x":1088,"y":640},{"gid":20,"height":64,"id":6,"name":"","rotation":0,"type":"","visible":true,"width":64,"x":1120,"y":704},{"height":32,"id":7,"name":"","properties":{"dx":0,"dy":-3,"group":5},"propertytypes":{"dx":"float","dy":"float","group":"int"},"rotation":0,"type":"platform","visible":true,"width":96,"x":160,"y":288},{"gid":17,"height":64,"id":8,"name":"","properties":{"group":4},"propertytypes":{"group":"int"},"rotation":0,"type":"","visible":true,"width":64,"x":256,"y":736},{"gid":16,"height":64,"id":9,"name":"","rotation":0,"type":"","visible":true,"width":64,"x":432,"y":736},{"height":32,"id":10,"name":"","properties":{"dx":3,"dy":0,"group":4},"propertytypes":{"dx":"float","dy":"float","group":"int"},"rotation":0,"type":"platform","visible":true,"width":96,"x":416,"y":544},{"gid":42,"height":96,"id":15,"name":"","properties":{"length":13},"propertytypes":{"length":"float"},"rotation":-90,"type":"","visible":true,"width":64,"x":128,"y":736},{"height":96,"id":18,"name":"","properties":{"dx":0,"dy":3,"group":7},"propertytypes":{"dx":"float","dy":"float","group":"int"},"rotation":0,"type":"platform","visible":true,"width":32,"x":128,"y":608},{"gid":18,"height":64,"id":20,"name":"","properties":{"group":5},"propertytypes":{"group":"int"},"rotation":0,"type":"","visible":true,"width":64,"x":320,"y":320},{"height":32,"id":23,"name":"","properties":{"dx":0,"dy":-4,"group":6},"propertytypes":{"dx":"float","dy":"float","group":"int"},"rotation":0,"type":"platform","visible":true,"width":96,"x":800,"y":448},{"gid":16,"height":64,"id":24,"name":"","properties":{"group":6},"propertytypes":{"group":"int"},"rotation":0,"type":"","visible":true,"width":64,"x":816,"y":192},{"gid":16,"height":64,"id":28,"name":"","properties":{"group":7},"propertytypes":{"group":"int"},"rotation":0,"type":"","visible":true,"width":64,"x":544,"y":192},{"height":32,"id":29,"name":"","properties":{"dx":3,"dy":0,"group":2,"paddingY":0},"propertytypes":{"dx":"float","dy":"float","group":"int","paddingY":"float"},"rotation":0,"type":"platform","visible":true,"width":96,"x":1056,"y":160},{"gid":16,"height":64,"id":30,"name":"","properties":{"group":2},"propertytypes":{"group":"int"},"rotation":0,"type":"","visible":true,"width":64,"x":944,"y":352},{"gid":20,"height":64,"id":31,"name":"","rotation":0,"type":"","visible":true,"width":64,"x":1120,"y":160}],"opacity":1,"type":"objectgroup","visible":true,"x":0,"y":0},{"draworder":"topdown","name":"Chars","objects":[{"gid":34,"height":64,"id":11,"name":"","rotation":0,"type":"","visible":true,"width":64,"x":336,"y":160},{"gid":35,"height":64,"id":12,"name":"","rotation":0,"type":"","visible":true,"width":64,"x":208,"y":160},{"gid":32,"height":64,"id":13,"name":"","rotation":0,"type":"","visible":true,"width":64,"x":176,"y":576},{"gid":33,"height":64,"id":14,"name":"","rotation":0,"type":"","visible":true,"width":64,"x":240,"y":576},{"gid":36,"height":64,"id":32,"name":"","rotation":0,"type":"","visible":true,"width":64,"x":816,"y":432},{"gid":37,"height":64,"id":33,"name":"","rotation":0,"type":"","visible":true,"width":64,"x":624,"y":272},{"gid":37,"height":64,"id":34,"name":"","rotation":0,"type":"","visible":true,"width":64,"x":360,"y":416},{"gid":36,"height":64,"id":35,"name":"","rotation":0,"type":"","visible":true,"width":64,"x":608,"y":560},{"gid":37,"height":64,"id":36,"name":"","rotation":0,"type":"","visible":true,"width":64,"x":48,"y":608},{"gid":36,"height":64,"id":37,"name":"","rotation":0,"type":"","visible":true,"width":64,"x":48,"y":448},{"gid":36,"height":64,"id":38,"name":"","rotation":0,"type":"","visible":true,"width":64,"x":912,"y":592},{"gid":37,"height":64,"id":39,"name":"","rotation":0,"type":"","visible":true,"width":64,"x":1056,"y":416},{"gid":36,"height":64,"id":43,"name":"","rotation":0,"type":"","visible":true,"width":64,"x":1200,"y":624},{"gid":37,"height":64,"id":44,"name":"","rotation":0,"type":"","visible":true,"width":64,"x":672,"y":144}],"opacity":1,"type":"objectgroup","visible":true,"x":0,"y":0}],"nextobjectid":45,"orientation":"orthogonal","renderorder":"right-down","tiledversion":"1.1.6","tileheight":32,"tilesets":[{"firstgid":1,"source":"../../../../assets/tilemaps/tilesets/Ground.json"},{"firstgid":16,"source":"../../../../assets/tilemaps/tilesets/Objects.json"},{"firstgid":32,"source":"../../../../assets/tilemaps/tilesets/Chars.json"},{"firstgid":40,"source":"../../../../assets/tilemaps/tilesets/LargeObjects.json"}],"tilewidth":32,"type":"map","version":1,"width":41}